{"imagenPersonaje":"C:\\fakepath\\Razor.png","imagenElemento":"C:\\fakepath\\Element_Electro.png","personaje":"Razor","numero":"1","tipo":"DPS","descripcion":"Razor es uno de los mejores DPS de cuatro estrellas de Genshin Impact, su potencial reside en lo fuerte que se hace al usar su habilidad definitiva. Sus escalados de daño son también increíbles.","arma1":"C:\\fakepath\\Lapida_del_Lobo.png","nombreArma1":"Lápida del lobo(5⭐)","arma2":"C:\\fakepath\\Médula_de_la_Serpiente_Marina.png","nombreArma2":"Médula de la serpiente marina(4⭐)","stat1":"ATK","stat2":"Bono daño Físico","stat3":"Daño crítico","artefacto1":"C:\\fakepath\\Gladiador.png","nombreArtefacto1":"Final del gladiador x4","artefacto2":"C:\\fakepath\\Gladiador.png","nombreArtefacto2":"Final del Gladiador x4"}